Metadata-Version: 2.4
Name: tyger-dev
Version: 0.0.6
Summary: Tyger is a simple type analysis tool that provides the foundations to implement diferent typing disciplines in Python.
Project-URL: Homepage, https://github.com/pleiad/GPython
Author-email: Cristóbal Ardiles <cristobalardiles.quiroz@gmail.com>, Matías Toro <mtoro@dcc.uchile.cl>, Martín Ramírez <martin.ramirez@ug.uchile.com>
License-File: LICENSE
Classifier: License :: OSI Approved :: MIT License
Classifier: Operating System :: OS Independent
Classifier: Programming Language :: Python :: 3
Requires-Python: >=3.10
Provides-Extra: dev
Requires-Dist: pytest; extra == 'dev'
